retirement/__init__.py
retirement/retirementPkg.py
retirement-0.1.3.dist-info/LICENSE
retirement-0.1.3.dist-info/METADATA
retirement-0.1.3.dist-info/WHEEL
retirement-0.1.3.dist-info/top_level.txt
retirement-0.1.3.dist-info/RECORD
