Metadata-Version: 2.1
Name: retirement
Version: 0.1.3
Summary: retirement calculations
Home-page: https://github.com/pstrito/RetirementPip.git
Author: Example Author
Author-email: author@example.com
Classifier: Programming Language :: Python :: 3
Classifier: License :: OSI Approved :: MIT License
Classifier: Operating System :: OS Independent
License-File: LICENSE
